package/__init__.py
package/module.py
ultimate_python_project_template-0.1.0.dist-info/LICENSE
ultimate_python_project_template-0.1.0.dist-info/METADATA
ultimate_python_project_template-0.1.0.dist-info/WHEEL
ultimate_python_project_template-0.1.0.dist-info/top_level.txt
ultimate_python_project_template-0.1.0.dist-info/RECORD
