Metadata-Version: 2.1
Name: ultimate-python-project-template
Version: 0.1.0
Summary: The ultimate Python project template
Home-page: https://github.com/TheRenegadeCoder/ultimate-python-project-template
Author: The Renegade Coder
Author-email: jeremy.grifski@therenegadecoder.com
License: UNKNOWN
Platform: UNKNOWN
Classifier: Development Status :: 1 - Planning
Classifier: License :: OSI Approved :: MIT License
Classifier: Programming Language :: Python :: 3
Classifier: Operating System :: OS Independent
Classifier: Topic :: Documentation :: Sphinx
Requires-Python: >=3.6
License-File: LICENSE
